_tests/__init__.py
_tests/test_strings.py
cingik/__init__.py
cingik/strings.py
cingik-0.1.1.dist-info/LICENSE
cingik-0.1.1.dist-info/METADATA
cingik-0.1.1.dist-info/WHEEL
cingik-0.1.1.dist-info/top_level.txt
cingik-0.1.1.dist-info/RECORD
