Metadata-Version: 2.1
Name: cingik
Version: 0.1.1
Summary: Describe your package in one sentence
Home-page: https://github.com/cicingik/cingik.git
Author: Dany Satyanegara
Author-email: danysatyanegara@gmail.com
License: MIT License
Platform: UNKNOWN
Requires-Dist: numpy
Requires-Dist: pandas
